ligoauth/__init__.py
ligoauth/ligoauth.py
ligoauth-0.1.0.dist-info/METADATA
ligoauth-0.1.0.dist-info/WHEEL
ligoauth-0.1.0.dist-info/top_level.txt
ligoauth-0.1.0.dist-info/RECORD
