Metadata-Version: 2.1
Name: ligoauth
Version: 0.1.0
Summary: ligo upload mac sdk
Requires-Python: >=3.6
